{"status":"OK","request_id":"4a5ce8fe-aa26-482d-8e44-07608779c693","parameters":{"query":"Teacher","page":1,"num_pages":1,"country":"us","language":"en"},"data":[{"job_id":"5C0LwXZoY9lyrI4KAAAAAA==","job_title":"MS\/HS Teacher","employer_name":"DC International School","employer_logo":"https:\/\/encrypted-tbn0.gstatic.com\/images?q=tbn:ANd9GcQBtsW34cynWiNtvJqx3FuPnbHOSxsgIlv4Tvx3&s=0","employer_website":"https:\/\/dcinternationalschool.org","job_publisher":"Indeed","job_employment_type":"Full-time","job_employment_types":["FULLTIME"],"job_apply_link":"https:\/\/www.indeed.com\/viewjob?jk=125568aee9129245&utm_campaign=google_jobs_apply&utm_source=google_jobs_apply&utm_medium=organic","job_apply_is_direct":true,"apply_options":[{"publisher":"Indeed","apply_link":"https:\/\/www.indeed.com\/viewjob?jk=125568aee9129245&utm_campaign=google_jobs_apply&utm_source=google_jobs_apply&utm_medium=organic","is_direct":true},{"publisher":"Glassdoor","apply_link":"https:\/\/www.glassdoor.com\/job-listing\/ms-hs-teacher-dc-international-school-JV_IC1138213_KO0,13_KE14,37.htm?jl=1009815073956&utm_campaign=google_jobs_apply&utm_source=google_jobs_apply&utm_medium=organic","is_direct":true},{"publisher":"SimplyHired","apply_link":"https:\/\/www.simplyhired.com\/job\/IuAy2oRqmyTbOkZ5ihUUt18LaVPi-7uoSDdc9j6zhcUyv-l-4s-2GA?utm_campaign=google_jobs_apply&utm_source=google_jobs_apply&utm_medium=organic","is_direct":false},{"publisher":"Jobrapido","apply_link":"https:\/\/us.jobrapido.com\/jobpreview\/2797662894701936640?utm_campaign=google_jobs_apply&utm_source=google_jobs_apply&utm_medium=organic","is_direct":true}],"job_description":"Position Overview: DCI is hiring a full-time Middle\/High School Teacher ( MS Math, HS ELL Teacher). This teaching position entails instructional and planning responsibilities for providing IB Social Studies education to students at DCI during the school year. This content will be taught in their target language English, Spanish, French or Chinese.\n\nSalary Range: $63,113 - $105,575 (Starting salary is determined by education and years of relevant experience)\n\nQualifications:\n\u2022 Bachelor's Degree is required.\n\u2022 A Master's Degree in secondary education or this content area is preferred.\n\u2022 Previous experience teaching in this content area is strongly preferred.\n\u2022 Ability to use multiple technology platforms to guide instruction and communicate with students and families and proficiency with communicating using G-Suite tools, including Gmail, is preferred.\n\u2022 Strong written and oral communication skills.\n\u2022 Clear a background check.\n\nKey Qualities & Skills:\n\u2022 Bilingual and biliterate in Spanish, French or Chinese.\n\u2022 Plan lessons using a deep understanding of, and integration with, the IB Social Studies Education curriculum framework.\n\u2022 Deliver exceptional Social Studies instruction, through immersion methods, to diverse learners in a culturally responsive manner.\n\u2022 Advise students, including teaching an advisory class using our advisory curriculum, and support other aspects of the school\u2019s instructional program.\n\u2022 Ability to handle the intensity required to work in a high-performing charter school, and remain organized, responsible, and accountable.\n\u2022 Ability to proactively manage the classroom learning environment in accordance with the school\u2019s discipline approach to maximize student engagement and learning.\n\u2022 Ability to accept and implement feedback received for real-time improvement.\n\u2022 Interest and desire to engage in the IB MYP\/DP and language immersion.\n\u2022 Embrace professional development through attending coaching meetings, school\/content-based sessions, and external development opportunities to deliver instruction at a high level.\n\u2022 Collaborate with general and special educators, coordinators, and leadership.\n\u2022 High degree of communication through a variety of mediums with parents and students.\n\u2022 Embrace French, Spanish, and Chinese cultures by leading and participating in cultural activities for faculty and students.\n\u2022 Ensure that our 1:1 Chromebooks program is implemented effectively for students by infusing technology into instruction.\n\u2022 Other duties as assigned.\n\nJob Type: Full-time\n\nPay: $63,113.00 - $105,575.00 per year\n\nBenefits:\n\u2022 401(k)\n\u2022 Dental insurance\n\u2022 Flexible schedule\n\u2022 Health insurance\n\u2022 Life insurance\n\u2022 Paid time off\n\u2022 Retirement plan\n\u2022 Vision insurance\n\nApplication Question(s):\n\u2022 What teaching subject are you interested in teaching? MS Math or HS ELL\n\nAbility to Commute:\n\u2022 Washington, DC 20012 (Required)\n\nAbility to Relocate:\n\u2022 Washington, DC 20012: Relocate before starting work (Required)\n\nWork Location: In person","job_is_remote":false,"job_posted_at":null,"job_posted_at_timestamp":null,"job_posted_at_datetime_utc":null,"job_location":"Washington, DC","job_city":"Washington","job_state":"District of Columbia","job_country":"US","job_latitude":38.9071923,"job_longitude":-77.0368707,"job_benefits":["paid_time_off","dental_coverage","health_insurance"],"job_google_link":"https:\/\/www.google.com\/search?q=jobs&gl=us&hl=en&udm=8#vhid=vt%3D20\/docid%3D5C0LwXZoY9lyrI4KAAAAAA%3D%3D&vssid=jobs-detail-viewer","job_min_salary":63113,"job_max_salary":105575,"job_salary_period":"YEAR","job_highlights":{"Qualifications":["Bachelor's Degree is required","Strong written and oral communication skills","Clear a background check","Bilingual and biliterate in Spanish, French or Chinese","Plan lessons using a deep understanding of, and integration with, the IB Social Studies Education curriculum framework","Ability to handle the intensity required to work in a high-performing charter school, and remain organized, responsible, and accountable","Ability to proactively manage the classroom learning environment in accordance with the school\u2019s discipline approach to maximize student engagement and learning","Ability to accept and implement feedback received for real-time improvement","Interest and desire to engage in the IB MYP\/DP and language immersion","Embrace French, Spanish, and Chinese cultures by leading and participating in cultural activities for faculty and students","MS Math or HS ELL","Washington, DC 20012 (Required)","Washington, DC 20012: Relocate before starting work (Required)"],"Benefits":["Salary Range: $63,113 - $105,575 (Starting salary is determined by education and years of relevant experience)","Pay: $63,113.00 - $105,575.00 per year","401(k)","Dental insurance","Flexible schedule","Health insurance","Life insurance","Paid time off","Retirement plan","Vision insurance"],"Responsibilities":["This teaching position entails instructional and planning responsibilities for providing IB Social Studies education to students at DCI during the school year","This content will be taught in their target language English, Spanish, French or Chinese","Deliver exceptional Social Studies instruction, through immersion methods, to diverse learners in a culturally responsive manner","Advise students, including teaching an advisory class using our advisory curriculum, and support other aspects of the school\u2019s instructional program","Embrace professional development through attending coaching meetings, school\/content-based sessions, and external development opportunities to deliver instruction at a high level","Collaborate with general and special educators, coordinators, and leadership","High degree of communication through a variety of mediums with parents and students","Ensure that our 1:1 Chromebooks program is implemented effectively for students by infusing technology into instruction","Other duties as assigned"]},"job_onet_soc":"25203100","job_onet_job_zone":"4"},{"job_id":"2NqjUsTWKPArNvHrAAAAAA==","job_title":"ELA Teacher, Grade 3 (SY25-26)","employer_name":"MERIDIAN PUBLIC CHARTER SCHOOL","employer_logo":"https:\/\/encrypted-tbn0.gstatic.com\/images?q=tbn:ANd9GcRNVORaXRCcZFyydT1oo7_ZBa7STnOh1j4j1xnE&s=0","employer_website":null,"job_publisher":"Indeed","job_employment_type":"Full-time","job_employment_types":["FULLTIME"],"job_apply_link":"https:\/\/www.indeed.com\/viewjob?jk=8e932d4317dc0c56&utm_campaign=google_jobs_apply&utm_source=google_jobs_apply&utm_medium=organic","job_apply_is_direct":false,"apply_options":[{"publisher":"Indeed","apply_link":"https:\/\/www.indeed.com\/viewjob?jk=8e932d4317dc0c56&utm_campaign=google_jobs_apply&utm_source=google_jobs_apply&utm_medium=organic","is_direct":false},{"publisher":"BeBee","apply_link":"https:\/\/us.bebee.com\/job\/a98ed12b57779a2a2261218ef58acac0?utm_campaign=google_jobs_apply&utm_source=google_jobs_apply&utm_medium=organic","is_direct":false}],"job_description":"ABOUT MERIDIAN PCS\n\nMeridian is a PreK-8th grade school located in Washington DC\u2019s vibrant U Street Corridor. Our mission is to inspire a passion for learning in our students and to help them build their self-confidence and self-respect through academic achievement. As one of the oldest public charter schools in the city, our campuses support about 600 racially and ethnically diverse students from all wards of Washington, DC. Approximately 25% of our students are English language learners (multilingual learners). One-third of students live in the surrounding neighborhood and approximately 50% live in Ward 1. Meridian\u2019s elementary PreK-5th grade campus is located in DC\u2019s vibrant U Street Corridor. Meridian\u2019s middle school campus, grades 6-8, is located in the Columbia Heights neighborhood.\n\nMeridian draws on the strengths of our neighborhood and our partnerships with community organizations to support our students and families. The city is our classroom; as an emerging EL Education school, we prepare our students to be active citizens and create a better world. Through language learning, a rich and rigorous curriculum, and the schoolwide values of curiosity, respect, resilience, and leadership, we support students in achieving their highest aspirations.\n\nJoin us as we continue to take Meridian from good to great! For additional information about Meridian visit mpcs-dc.org.\n\nABOUT THE POSITION\n\nWe are seeking an ELA Teacher to work with our third grade students for the 2025-26 school year. All positions are full-time, salaried, 10-month positions.\n\nTeachers at Meridian are responsible for the following:\n\u2022 Collaborating with colleagues in developing cohesive Common Core-aligned curriculum materials, integrating instructional resources, and establishing instructional goals\n\u2022 Preparing standards-based lessons that challenge students\u2019 critical thinking\n\u2022 Utilizing strong content knowledge to effectively present enticing and rigorous Common Core-aligned lessons\n\u2022 Differentiating instruction to accommodate multiple learning styles and abilities\n\u2022 Assessing students\u2019 academic and developmental growth through observation and a variety of assessment methods\n\u2022 Tracking and monitoring assessment results in order to regularly refine teaching practices and design differentiated lesson plans\n\u2022 Applying the values of urgency, rigor, and consistency to create a positive learning environment that promotes high expectations\n\u2022 Communicating with students, parents, school staff to ensure that students are on-track in their learning and making progress towards goals\n\u2022 Establishing and implementing effective classroom management procedures, and maintain a productive, safe, and focused learning environment\n\u2022 Other duties as assigned\n\nQUALIFICATIONS\n\nIdeal candidates will have the following education and experience:\n\u2022 Bachelor\u2019s degree required. Concentration or advanced degree in education or preferred.\n\u2022 Two or more years of teaching experience as a K-12 teacher in an urban environment with a strong record of student achievement preferred\n\u2022 Experience\/strength in the content area preferred\n\u2022 Spanish language skills a plus\n\nSALARY AND BENEFITS\n\nMeridian teachers and staff are compensated competitively for their time and have opportunities to earn additional income through leadership opportunities at the school level, offering extracurricular clubs and sports for students, and facilitating tutoring programs. In the 2024-25 school year, the pay scale for teachers ranged from $61,000 -$99,000, based on level of education and years of experience.\n\nHOW TO APPLY\n\nDo you embody a love of learning? Do you believe in the importance of educating the whole child? Do you want to help Meridian continue to grow from good to great? Apply today!\n\nNO PHONE CALLS PLEASE.\n\nMeridian Public Charter School is an Equal Opportunity Employer. The School\u2019s EEO policy prohibits discrimination in employment based on race, color, religion, national origin, disability, sex, age, sexual orientation, marital status, or any other basis prohibited by applicable law. Meridian PCS prohibits discrimination against individuals with disabilities and will reasonably accommodate applicants with a disability, upon request, and will also ensure reasonable accommodation for employees with a disability. Under this policy, equal employment opportunity is required in recruitment, hiring, training and development, promotion, termination, compensation, benefits, and all other terms, conditions, and privileges of employment as required by applicable law.\n\nJob Type: Full-time\n\nPay: $61,000.00 - $99,000.00 per year\n\nWork Location: In person","job_is_remote":false,"job_posted_at":null,"job_posted_at_timestamp":null,"job_posted_at_datetime_utc":null,"job_location":"Washington, DC","job_city":"Washington","job_state":"District of Columbia","job_country":"US","job_latitude":38.9071923,"job_longitude":-77.0368707,"job_benefits":null,"job_google_link":"https:\/\/www.google.com\/search?q=jobs&gl=us&hl=en&udm=8#vhid=vt%3D20\/docid%3D2NqjUsTWKPArNvHrAAAAAA%3D%3D&vssid=jobs-detail-viewer","job_min_salary":61000,"job_max_salary":99000,"job_salary_period":"YEAR","job_highlights":{"Qualifications":["Bachelor\u2019s degree required"],"Benefits":["SALARY AND BENEFITS","Meridian teachers and staff are compensated competitively for their time and have opportunities to earn additional income through leadership opportunities at the school level, offering extracurricular clubs and sports for students, and facilitating tutoring programs","In the 2024-25 school year, the pay scale for teachers ranged from $61,000 -$99,000, based on level of education and years of experience","Pay: $61,000.00 - $99,000.00 per year"],"Responsibilities":["All positions are full-time, salaried, 10-month positions","Collaborating with colleagues in developing cohesive Common Core-aligned curriculum materials, integrating instructional resources, and establishing instructional goals","Preparing standards-based lessons that challenge students\u2019 critical thinking","Utilizing strong content knowledge to effectively present enticing and rigorous Common Core-aligned lessons","Differentiating instruction to accommodate multiple learning styles and abilities","Assessing students\u2019 academic and developmental growth through observation and a variety of assessment methods","Tracking and monitoring assessment results in order to regularly refine teaching practices and design differentiated lesson plans","Applying the values of urgency, rigor, and consistency to create a positive learning environment that promotes high expectations","Communicating with students, parents, school staff to ensure that students are on-track in their learning and making progress towards goals","Establishing and implementing effective classroom management procedures, and maintain a productive, safe, and focused learning environment","Other duties as assigned"]},"job_onet_soc":"25202100","job_onet_job_zone":"4"},{"job_id":"TrK1vWNyjMhfExZHAAAAAA==","job_title":"Rocketbooster Teacher (Before\/Aftercare- Part time-DC","employer_name":"Rocketship Public Schools","employer_logo":"https:\/\/encrypted-tbn0.gstatic.com\/images?q=tbn:ANd9GcTW6GuJ2r8bI4m8_7UCCo5F6gVvXPNOpJj0Ltzw&s=0","employer_website":"https:\/\/www.rocketshipschools.org","job_publisher":"LinkedIn","job_employment_type":"Part-time","job_employment_types":["PARTTIME"],"job_apply_link":"https:\/\/www.linkedin.com\/jobs\/view\/rocketbooster-teacher-before-aftercare-part-time-dc-at-rocketship-public-schools-4293115752?utm_campaign=google_jobs_apply&utm_source=google_jobs_apply&utm_medium=organic","job_apply_is_direct":false,"apply_options":[{"publisher":"LinkedIn","apply_link":"https:\/\/www.linkedin.com\/jobs\/view\/rocketbooster-teacher-before-aftercare-part-time-dc-at-rocketship-public-schools-4293115752?utm_campaign=google_jobs_apply&utm_source=google_jobs_apply&utm_medium=organic","is_direct":false},{"publisher":"Indeed","apply_link":"https:\/\/www.indeed.com\/viewjob?jk=ebb81f6a4d92b63b&utm_campaign=google_jobs_apply&utm_source=google_jobs_apply&utm_medium=organic","is_direct":false},{"publisher":"JobLeads","apply_link":"https:\/\/www.jobleads.com\/us\/job\/rocketbooster-teacher-before-aftercare-part-time-dc--washington--e29dba8d8740f4fd72bd73a3cce0d8be8?utm_campaign=google_jobs_apply&utm_source=google_jobs_apply&utm_medium=organic","is_direct":false},{"publisher":"Learn4Good","apply_link":"https:\/\/www.learn4good.com\/jobs\/washington\/district-of-columbia\/education\/4580271467\/e\/?utm_campaign=google_jobs_apply&utm_source=google_jobs_apply&utm_medium=organic","is_direct":false}],"job_description":"At Rocketship Public Schools, we believe in the infinite possibility of human potential. We believe that every student deserves the right to dream, to discover, and to develop their unique potential. And it is our responsibility and our privilege to unleash the potential inside every Rocketeer we serve. Our non-profit network of public elementary charter schools propels student achievement, develops exceptional educators, and partners with parents who enable high-quality public schools to thrive in their community. We are a collective of parents, teachers, leaders, and students working together to transform the future for underserved communities across our country. At Rocketship Public Schools, we are unleashing potential.\n\nRocketbooster Teachers will provide before and aftercare support to Rocketeers under the direction and supervision of the School Site Manager and Senior Manager of Extended Learning. This position is responsible for ensuring that the day-to-day operations of before and aftercare of the school site run safely and smoothly. Furthermore, Rocketbooster Teachers are responsible for facilitating high-quality enrichment, academic, and specialized wellness activities that support Rocketeer Achievement. They will work at one of our three campuses in Washington, DC.\n\nEssential Functions\n\u2022 Supervise and monitor students during assigned aftercare hours including during aftercare sessions\n\u2022 Implement all site rules and safety regulations within the structure of the Rocketship classroom culture and in adherence to OSSE regulations\n\u2022 Plan, internalize, and implement lesson plans and daily age appropriate activities for students in the classroom\n\u2022 Report any unsafe conditions, including equipment, to administrators immediately\n\u2022 Partner with school staff to ensure a safe and effective arrival\/dismissal for all students before and after school hours\n\u2022 Utilize appropriate disciplinary procedures and techniques in accordance with the school site discipline plan\n\u2022 Ensure all proactive, positive behavior incentive systems are actively used in the classrooms\n\u2022 Attend staff meetings and in-service training as deemed necessary for the position\n\u2022 Facilitate academic, enrichment, and wellness activities to support Rocketeer growth and development.\n\u2022 Communicate regularly with families of students to build relationships, and share progress and important updates\n\u2022 Builds relationships and liaises with other all staff and families to drive collaboration and program success\n\u2022 Ensures all aspects of the Rocketbooster program are implemented with fidelity\n\u2022 All other duties as assigned and appropriate by the Site Manager\n\nRequired Qualifications\n\u2022 Compliance Qualifications\n\u2022 Must be 18 years old and meet at least one of the following:\n\u2022 Associates or more advanced degree with a major in early childhood or a closely related field\n\u2022 Associate\u2019s or more advanced degree in an unrelated field and have earned at least 24 credit hours in early childhood education, or a closely related field, AND have at least one year of supervised occupational experience working with children in a licensed DC Child Development Center or equivalent in another jurisdiction\n\u2022 Earned at least 48 credit hours, or its recognized equivalent, of which 15 credit hours in early childhood education or a closely related field, AND have at two years of supervised occupational experience working with children in a licensed DC Child Development Center or equivalent in another jurisdiction; provided he or she earns an Associates degree by Dec. 2024\n\u2022 Earned a high school diploma, or its equivalent and a current CDA credential (with the specified age classification), AND must earn an Associate\u2019s degree in the desired field by Dec. 2024\n\u2022 Position Qualifications:\n\u2022 Commitment to Rocketship's mission, vision, and goals\n\u2022 Passion for working with children\n\u2022 Previous experience managing and\/or teaching groups of elementary-age students is strongly preferred\n\u2022 Excellent communication and interpersonal skills, with ability to engage and work closely with a wide range of staff members\n\u2022 Ability to learn laws, rules, practices and procedures related to public education and specific to Rocketship Public Schools\n\u2022 Flexibility and a willingness to learn\n\u2022 Strong commitment to supporting Rocketship students and community\n\u2022 Excellent writing and communication skills and the ability to build relationships with program leaders, community members, and families\n\u2022 Highly organized, able to multitask, and consistently meet deadlines\n\u2022 Experience with online learning tools, databases, and Google Suite programming\n\u2022 Due to OSSE standards, all aftercare staff are responsible for maintaining compliance standards including:\n\u2022 Child and Family Services Agency ( Child Protection Registry check),\n\u2022 a local fingerprint database check,\n\u2022 Drug and Alcohol Testing,\n\u2022 tuberculosis testing, and\n\u2022 CPR\/First Aid certification and other continuing education training as well\n\nThis is a part-time position; typical work hours are 2:00 pm - 7:00pm, but may include additional hours for trainings , meetings, and other events. Pay is commensurate with education and experience.\n\nPhysical Demands\n\nThe physical demands described here are representative of those that must be met by an employee to successfully perform the essential functions of this position. Reasonable accommodations may be made to enable individuals with disabilities to perform the functions. While performing the duties of this position, the employee is regularly required to talk, hear, and communicate with both adults and children. The employee frequently is required to use hands or fingers, handle or feel objects, tools, or controls. The employee is frequently required to stand; walk; sit; and reach with hands and arms. The employee must occasionally lift and\/or move up to 50 pounds and occasionally climb ladders. Specific vision abilities required by this position include close vision, distance vision, and the ability to adjust focus. The noise level in the work environment is moderate to high.\n\nCompensation\n\nCommensurate with qualifications and experience.\n\nRocketship Public Schools provides equal employment opportunities (EEO) to all employees and applicants for employment without regard to race, color, religion, gender, sexual orientation, national origin, age, disability, genetic information, marital status, amnesty, or status as a covered veteran in accordance with applicable federal, state and local laws. Rocketship Public Schools complies with applicable state and local laws governing non-discrimination in employment in every location in which the company has facilities. This policy applies to all terms and conditions of employment, including, but not limited to, hiring, placement, promotion, termination, layoff, recall, transfer, leaves of absence, compensation, and training.\n\nRocketship Public Schools expressly prohibits any form of unlawful employee harassment based on race, color, religion, gender, sexual orientation, national origin, age, genetic information, disability, or veteran status. Improper interference with the ability of Rocketship Public Schools\u2019 employees to perform their expected job duties is absolutely not tolerated. Click here for our Sexual Harassment Policy and here for our Title IX Policy . For questions, concerns, or complaints, please contact Equity\/Discrimination Title IX Compliance Officer, Kenzie Kilb. Email: [email protected] . Address: 350 Twin Dolphin Drive, Suite 109, Redwood City, CA 94065. Phone: 877-806-0920 ext. 115.","job_is_remote":false,"job_posted_at":null,"job_posted_at_timestamp":null,"job_posted_at_datetime_utc":null,"job_location":"Washington, DC","job_city":"Washington","job_state":"District of Columbia","job_country":"US","job_latitude":38.9071923,"job_longitude":-77.0368707,"job_benefits":null,"job_google_link":"https:\/\/www.google.com\/search?q=jobs&gl=us&hl=en&udm=8#vhid=vt%3D20\/docid%3DTrK1vWNyjMhfExZHAAAAAA%3D%3D&vssid=jobs-detail-viewer","job_salary":null,"job_min_salary":null,"job_max_salary":null,"job_salary_period":null,"job_highlights":{"Qualifications":["Compliance Qualifications","Must be 18 years old and meet at least one of the following:","Associates or more advanced degree with a major in early childhood or a closely related field","Associate\u2019s or more advanced degree in an unrelated field and have earned at least 24 credit hours in early childhood education, or a closely related field, AND have at least one year of supervised occupational experience working with children in a licensed DC Child Development Center or equivalent in another jurisdiction","Earned at least 48 credit hours, or its recognized equivalent, of which 15 credit hours in early childhood education or a closely related field, AND have at two years of supervised occupational experience working with children in a licensed DC Child Development Center or equivalent in another jurisdiction; provided he or she earns an Associates degree by Dec. 2024","Commitment to Rocketship's mission, vision, and goals","Passion for working with children","Excellent communication and interpersonal skills, with ability to engage and work closely with a wide range of staff members","Ability to learn laws, rules, practices and procedures related to public education and specific to Rocketship Public Schools","Flexibility and a willingness to learn","Strong commitment to supporting Rocketship students and community","Excellent writing and communication skills and the ability to build relationships with program leaders, community members, and families","Highly organized, able to multitask, and consistently meet deadlines","Experience with online learning tools, databases, and Google Suite programming","Due to OSSE standards, all aftercare staff are responsible for maintaining compliance standards including:","Child and Family Services Agency ( Child Protection Registry check),","a local fingerprint database check,","Drug and Alcohol Testing,","tuberculosis testing, and","CPR\/First Aid certification and other continuing education training as well","The physical demands described here are representative of those that must be met by an employee to successfully perform the essential functions of this position","The employee frequently is required to use hands or fingers, handle or feel objects, tools, or controls","The employee is frequently required to stand; walk; sit; and reach with hands and arms","The employee must occasionally lift and\/or move up to 50 pounds and occasionally climb ladders","Specific vision abilities required by this position include close vision, distance vision, and the ability to adjust focus"],"Benefits":["Pay is commensurate with education and experience","Commensurate with qualifications and experience"],"Responsibilities":["Rocketbooster Teachers will provide before and aftercare support to Rocketeers under the direction and supervision of the School Site Manager and Senior Manager of Extended Learning","This position is responsible for ensuring that the day-to-day operations of before and aftercare of the school site run safely and smoothly","Furthermore, Rocketbooster Teachers are responsible for facilitating high-quality enrichment, academic, and specialized wellness activities that support Rocketeer Achievement","They will work at one of our three campuses in Washington, DC","Supervise and monitor students during assigned aftercare hours including during aftercare sessions","Implement all site rules and safety regulations within the structure of the Rocketship classroom culture and in adherence to OSSE regulations","Plan, internalize, and implement lesson plans and daily age appropriate activities for students in the classroom","Report any unsafe conditions, including equipment, to administrators immediately","Partner with school staff to ensure a safe and effective arrival\/dismissal for all students before and after school hours","Utilize appropriate disciplinary procedures and techniques in accordance with the school site discipline plan","Ensure all proactive, positive behavior incentive systems are actively used in the classrooms","Attend staff meetings and in-service training as deemed necessary for the position","Facilitate academic, enrichment, and wellness activities to support Rocketeer growth and development","Communicate regularly with families of students to build relationships, and share progress and important updates","Builds relationships and liaises with other all staff and families to drive collaboration and program success","Ensures all aspects of the Rocketbooster program are implemented with fidelity","All other duties as assigned and appropriate by the Site Manager","This is a part-time position; typical work hours are 2:00 pm - 7:00pm, but may include additional hours for trainings , meetings, and other events","Reasonable accommodations may be made to enable individuals with disabilities to perform the functions","While performing the duties of this position, the employee is regularly required to talk, hear, and communicate with both adults and children"]},"job_onet_soc":"39901100","job_onet_job_zone":"2"},{"job_id":"XQBSlSf-l-iADG5gAAAAAA==","job_title":"Early Childhood Lead Teacher (Pre-K through 1st Grade)","employer_name":"Creative Minds International Public Charter School","employer_logo":"https:\/\/encrypted-tbn0.gstatic.com\/images?q=tbn:ANd9GcSmVBbsJAVtj83TTEbD7mOOVO48Ev0T77wkAfLL&s=0","employer_website":"https:\/\/www.creativemindspcs.org","job_publisher":"ZipRecruiter","job_employment_type":"Full-time","job_employment_types":["FULLTIME"],"job_apply_link":"https:\/\/www.ziprecruiter.com\/c\/Creative-Minds-International-Public-Charter-School\/Job\/Early-Childhood-Lead-Teacher-(Pre-K-through-1st-Grade)\/-in-Washington,DC?jid=71397f5cda742737&utm_campaign=google_jobs_apply&utm_source=google_jobs_apply&utm_medium=organic","job_apply_is_direct":false,"apply_options":[{"publisher":"ZipRecruiter","apply_link":"https:\/\/www.ziprecruiter.com\/c\/Creative-Minds-International-Public-Charter-School\/Job\/Early-Childhood-Lead-Teacher-(Pre-K-through-1st-Grade)\/-in-Washington,DC?jid=71397f5cda742737&utm_campaign=google_jobs_apply&utm_source=google_jobs_apply&utm_medium=organic","is_direct":false}],"job_description":"Creative Minds International Public Charter School (CMIPCS) is a tuition-free public charter school located in NW Washington, DC, authorized to serve students from preschool through 8th grade. Now in its ninth year of operation, CMIPCS serves over 500 students in Preschool (3-year-olds) through 8th grade.\n\nOur mission is to provide students with the foundational skills required for successful participation in a global society. CMI is a unique and dynamic working environment with a respectful and positive school culture. We offer a highly-engaging, international curriculum with project- and arts-based activities with an emphasis in STEAM that foster creativity, self-motivation, social and emotional development, and academic excellence.\n\nThe Position:\n\nEarly Childhood Education (ECE) lead teachers at CMIPCS provide rich, age-appropriate learning experiences for the classroom of Pre-Kindergarten - 1st grade students. Early Childhood Education Lead teachers, along with 1 assistant teacher, utilize an international curriculum, along with arts-integration, play and inclusion practices to teach a diverse student body. They encourage and respect individuality, focusing on the development of each child's regulation and engagement in social-emotional learning and academic content. Responsibilities include, but are not limited to:\n\u2022 Establishing clear objectives for all lessons, units, projects, and assessments;\n\u2022 Developing lesson plans that draw content from CMI professional development in the areas of arts integration and child development to reinforce student learning;\n\u2022 Using a variety of instructional materials, resources, and experiences to enrich student learning;\n\u2022 Meeting the needs, interests and abilities for all students, including students with disabilities, ELL students, and those who are gifted and talented;\n\u2022 Administering CMI's developmental assessment for each child and tracking students' progress through the developmental milestones required for successful communication, self-regulation, and social interaction;\n\u2022 Regularly observing students and taking anecdotal notes to inform planning in the arrangement of small groups, classroom set up, integrations of students' interests in learning activities, and subsequent assessments;\n\u2022 Monitoring student progress through frequent formal and informal student evaluations recorded in portfolio assessments;\n\u2022 Providing educational opportunities that reflects an understanding of students' unique sensory and information processing profiles;\n\u2022 Using appropriate techniques and strategies that promote and enhance creative problem-solving, and evaluative thinking of students;\n\u2022 Working with families to support the progress of individual students;\n\u2022 Valuing the importance of play and providing opportunities for child-initiated explorations in the classroom throughout the day;\n\u2022 Using effective, positive, respectful interpersonal communication skills;\n\u2022 Establishing positive relationships with colleagues, students, families and the community which reflect recognition of and respect for every individual;\n\u2022 Willingness or experience incorporating instructional technology into practice;\n\u2022 Attend a two-week summer institute and other required professional development sessions.\n\nDesired Qualities\n\u2022 Excellent verbal\/written communication skills;\n\u2022 Demonstrated ability to engage the interest of school-age children;\n\u2022 Prior teaching experience, preferably in an elementary urban setting;\n\u2022 Demonstrated ability to work well with parents;\n\u2022 Demonstrated ability to work effectively with teaching teams;\n\u2022 Patience, flexibility, and a willingness to take risks;\n\u2022 Consistently reflects on her\/his own teaching practices;\n\u2022 Experience working with linguistically and ethnically diverse student populations and children with developmental differences;\n\u2022 Demonstrated commitment to professional growth and eagerness to learn;\n\u2022 Demonstrated commitment to the well-being and success of all students.\n\nMinimum Qualifications:\n\u2022 Bachelor's degree (required), Education degree (preferred);\n\u2022 Praxis I; Elementary Praxis II (successful completion preferred, eligibility required);\n\nCreative Minds International PCS is an Equal Opportunity Employer. Personnel are chosen on the basis of ability without regard to race, color, religion, sex, national origin, disability, marital status or sexual orientation, in accordance with federal and state law.","job_is_remote":false,"job_posted_at":null,"job_posted_at_timestamp":null,"job_posted_at_datetime_utc":null,"job_location":"Washington, DC","job_city":"Washington","job_state":"District of Columbia","job_country":"US","job_latitude":38.9071923,"job_longitude":-77.0368707,"job_benefits":null,"job_google_link":"https:\/\/www.google.com\/search?q=jobs&gl=us&hl=en&udm=8#vhid=vt%3D20\/docid%3DXQBSlSf-l-iADG5gAAAAAA%3D%3D&vssid=jobs-detail-viewer","job_salary":null,"job_min_salary":null,"job_max_salary":null,"job_salary_period":null,"job_highlights":{"Qualifications":["Establishing positive relationships with colleagues, students, families and the community which reflect recognition of and respect for every individual;","Willingness or experience incorporating instructional technology into practice;","Attend a two-week summer institute and other required professional development sessions"],"Responsibilities":["Early Childhood Education (ECE) lead teachers at CMIPCS provide rich, age-appropriate learning experiences for the classroom of Pre-Kindergarten - 1st grade students","Early Childhood Education Lead teachers, along with 1 assistant teacher, utilize an international curriculum, along with arts-integration, play and inclusion practices to teach a diverse student body","They encourage and respect individuality, focusing on the development of each child's regulation and engagement in social-emotional learning and academic content","Establishing clear objectives for all lessons, units, projects, and assessments;","Developing lesson plans that draw content from CMI professional development in the areas of arts integration and child development to reinforce student learning;","Using a variety of instructional materials, resources, and experiences to enrich student learning;","Meeting the needs, interests and abilities for all students, including students with disabilities, ELL students, and those who are gifted and talented;","Administering CMI's developmental assessment for each child and tracking students' progress through the developmental milestones required for successful communication, self-regulation, and social interaction;","Regularly observing students and taking anecdotal notes to inform planning in the arrangement of small groups, classroom set up, integrations of students' interests in learning activities, and subsequent assessments;","Monitoring student progress through frequent formal and informal student evaluations recorded in portfolio assessments;","Providing educational opportunities that reflects an understanding of students' unique sensory and information processing profiles;","Using appropriate techniques and strategies that promote and enhance creative problem-solving, and evaluative thinking of students;","Working with families to support the progress of individual students;","Valuing the importance of play and providing opportunities for child-initiated explorations in the classroom throughout the day;","Using effective, positive, respectful interpersonal communication skills;"]},"job_onet_soc":"25201100","job_onet_job_zone":"3"},{"job_id":"rWJ0wvsXBo0yQjamAAAAAA==","job_title":"Assistant Teacher - Infant Toddler","employer_name":"EducareDC","employer_logo":null,"employer_website":"https:\/\/www.educaredc.org","job_publisher":"Indeed","job_employment_type":"Full-time","job_employment_types":["FULLTIME"],"job_apply_link":"https:\/\/www.indeed.com\/viewjob?jk=e81a42cccaafba37&utm_campaign=google_jobs_apply&utm_source=google_jobs_apply&utm_medium=organic","job_apply_is_direct":false,"apply_options":[{"publisher":"Indeed","apply_link":"https:\/\/www.indeed.com\/viewjob?jk=e81a42cccaafba37&utm_campaign=google_jobs_apply&utm_source=google_jobs_apply&utm_medium=organic","is_direct":false},{"publisher":"ZipRecruiter","apply_link":"https:\/\/www.ziprecruiter.com\/c\/EducareDC\/Job\/Assistant-Teacher-Infant-Toddler\/-in-Washington,DC?jid=50481e4ec27f05e0&utm_campaign=google_jobs_apply&utm_source=google_jobs_apply&utm_medium=organic","is_direct":true},{"publisher":"LinkedIn","apply_link":"https:\/\/www.linkedin.com\/jobs\/view\/assistant-teacher-infant-toddler-at-educare-dc-4308717017?utm_campaign=google_jobs_apply&utm_source=google_jobs_apply&utm_medium=organic","is_direct":false},{"publisher":"JobTarget","apply_link":"https:\/\/www.jobtarget.com\/jobs\/jt-fnwd3c1qz7\/assistant-teacher-infant-toddler-washington-district-of-columbia?utm_campaign=google_jobs_apply&utm_source=google_jobs_apply&utm_medium=organic","is_direct":false},{"publisher":"Apply.appone.com","apply_link":"https:\/\/apply.appone.com\/job\/6734be27b452473565535a74?source=JobTarget&utm_campaign=google_jobs_apply&utm_source=google_jobs_apply&utm_medium=organic","is_direct":false},{"publisher":"Lensa","apply_link":"https:\/\/lensa.com\/job-v1\/educare-dc\/washington-dc\/assistant-teacher\/4d38aca6d9e43e23c57970fdea49b8b3?utm_campaign=google_jobs_apply&utm_source=google_jobs_apply&utm_medium=organic","is_direct":false},{"publisher":"Learn4Good","apply_link":"https:\/\/www.learn4good.com\/jobs\/washington\/district-of-columbia\/education\/4521031551\/e\/?utm_campaign=google_jobs_apply&utm_source=google_jobs_apply&utm_medium=organic","is_direct":false}],"job_description":"ORGANIZATIONAL OVERVIEW\n\nEducare DC serves over 350 children from birth to five years \u2013 and their families \u2013 through our state-of-the-art center and through community partnerships. Building on the program foundations of Early Head Start and Head Start and accredited by NAEYC, Educare DC promotes school readiness by providing high-quality, comprehensive early learning programming for children who are historically underserved due to systemic racism, eliminating the opportunity gap often experienced by low-income communities. Educare DC is part of the 25-school Educare Learning Network that serves as a platform for broader change, inspiring high-quality programs in communities, improving public policies nationally and within each state, and demonstrating a comprehensive, research-based approach to the first five years of life and learning. Educare DC draws on a blend of private and public dollars, including federal childcare funding, Early Head Start, Pre-K, and other state and federal funding streams.al funding streams.\n\nPOSITION OVERVIEW\n\nThe Infant-Toddler Assistant Teacher is responsible for contributing to the planning, implementation and coordination of the comprehensive education program. The Assistant Teacher supports the Lead Teacher in ensuring that the education program is developmentally appropriate and meets the individual needs of the children as mandated by Early Head Start, state and local standards and the Educare model.\n\nResponsibilities\n\nProgram Core Features of the Educare Model\n\nParticipate in training to build an understanding of the Educare Model\n\nParticipate in the local evaluation and national Educare Implementation Study, engaging in a system of reciprocal, regular data feedback and utilization for individualized planning for children and families and continuous program improvement\n\nParticipate in Reflective Practice and Supervision throughout the program\n\nProvide a high-quality early learning program that incorporates evidence-based curriculum and instructional activities\n\nSupport and provide continuity of care to help infants and toddlers develop secure relationships\n\nImplement, document, and demonstrate an understanding of the importance of multiple perspectives and have the skills to be successful in their interdisciplinary efforts\n\nCollaborate with the Family Engagement Specialist (assigned to each child), and other Educare personnel and support staff to promote individual children's goals relating to early communication development, fine and gross motor skills, development of social and self-care skills\n\nParticipate in Family Child Service Reviews as scheduled\n\nIn support of ongoing, intensive professional development, Assistant Teachers will attend and participate in all scheduled trainings, engage in coaching cycles with their Lead Teachers, and develop individual plans for their own professional development\n\nProvide an enhanced curriculum focus on: social emotional development, early language and literacy, physical development, and integration of the arts\n\nCurriculum\n\nEngage positively with the children and use appropriate discipline methods as outlined in the school's child guidance discipline policy\n\nAssist in the planning and implementation of learning experiences that promote all developmental domains (social, emotional, physical, and intellectual) including contributing to the readiness of children to enter school by developing their early language acquisition and vocabulary\n\nAssist in developing and managing an attractive and engaging environment that encourages exploration and fosters independence\n\nPosition themselves strategically in all environments to actively engage children, provide optimal supervision, and facilitate play\n\nUse the playground as an extension of the classroom; ensure that the playground is safe.\n\nAssist in daily routines such as bottle feedings, meal preparations, diapering, toileting, hand washing, monitoring sleep times, cleanup, and supervision of children at all times, including outdoor play\n\nAssessment\n\nCollaborate with the teaching team to observe, document, and assess their primary care children\n\nIdentify any developmental concerns for primary care children and share the information with the Lead Teacher\n\nCollaborate with the teaching team to develop activities and use instructional materials suitable for infants and toddlers with a wide range of cognitive, physical, and emotional maturities\n\nParticipate in Family Child Service Reviews for their primary children\n\nAssist in the completion of band-aid reports and documentation of incidents in the medical log\n\nHome\/School Connection:\n\nDevelop effective partnerships with families by maintaining open communication and encouraging their input into the educational program.\n\nCollaborate with the teaching team to develop, document, and implement, in collaboration with each child\u2019s family, an individualized plan for each child to be reviewed regularly in response to each child\u2019s progress\n\nUnder the direction of the Lead Teacher, and as feasible, participate in home visits and parent conferences\n\nOther\n\nThe Assistant Teacher will assume the responsibilities of the Lead Teacher in the absence of the Lead Teacher\n\nUnder the direction of the Lead Teacher, assist in data entry as requested\n\nAssist the Lead Teacher to maintain an up to date classroom inventory\n\nParticipate in reflective supervision with the Lead Teacher and\/or Master Teacher\n\nPerform other duties as assigned within the scope of the job description\n\nEXPERIENCE AND ABILITIES\n\n1 year of relevant experience\n\nKnowledge of early childhood curriculum and developmentally appropriate practice for the specific age group (6 weeks through three years)\n\nKnowledge of Early Head Start Performance Standards\n\nKnowledge of City and State licensing requirements\n\nAbility to work as a cooperative and supportive team member\n\nAbility to communicate and cooperate with various professionals and community groups.\n\nAbility to communicate and cooperate with parents\n\nAbility and willingness to work in a program located in a high-risk, low-income community\n\nResponsible for contributing to the planning, implementation and coordination of the comprehensive education program.\n\nSupports the Lead Teacher in ensuring that the education program is developmentally appropriate and meets the individual needs of the children as mandated by Head Start, state and local standards, and the Educare model.\n\nAssist with the implementation of all program requirements in adherence to performance and outcome standards, along with compliance standards, as prescribed by the multiple funding and model requirements.\n\nEDUCATION REQUIREMENTS\n\nAssociate's degree in early childhood education, Child Development or a related field\n\nADDITIONAL JOB REQUIREMENTS\n\nClearance of background check as required by local, state, and federal regulations.\n\nPhysical examination and diagnostic tests as required by local, state, and federal regulations.\n\nA drug screen and bi-annual TB tests are required as a condition of continual employment.\n\nFull Covid-19 vaccination is required as a condition of employment.\n\nESSENTIAL JOB FUNCTIONS\n\nMust be able to physically interact with children, including bending, kneeling, sitting on the floor, lifting up to 40 pounds, climbing and walking\n\nMust have advanced command of the English language and grammar, both verbal and written\n\nMust remain abreast of developments in the child development field to enhance professional growth and development\n\nAbout EducareDC\nEducare DC is a leading early childhood education program preparing children for success in kindergarten and beyond. With a focus on excellence and continuous improvement, the Educare DC work environment is fun, impactful, and rewarding. Come join our team and partner with us to provide the highest quality care and education to families.","job_is_remote":false,"job_posted_at":null,"job_posted_at_timestamp":null,"job_posted_at_datetime_utc":null,"job_location":"Washington, DC","job_city":"Washington","job_state":"District of Columbia","job_country":"US","job_latitude":38.9071923,"job_longitude":-77.0368707,"job_benefits":null,"job_google_link":"https:\/\/www.google.com\/search?q=jobs&gl=us&hl=en&udm=8#vhid=vt%3D20\/docid%3DrWJ0wvsXBo0yQjamAAAAAA%3D%3D&vssid=jobs-detail-viewer","job_min_salary":43865,"job_max_salary":54262,"job_salary_period":"YEAR","job_highlights":{"Qualifications":["1 year of relevant experience","Knowledge of early childhood curriculum and developmentally appropriate practice for the specific age group (6 weeks through three years)","Knowledge of Early Head Start Performance Standards","Knowledge of City and State licensing requirements","Ability to work as a cooperative and supportive team member","Ability to communicate and cooperate with various professionals and community groups","Ability to communicate and cooperate with parents","Ability and willingness to work in a program located in a high-risk, low-income community","Associate's degree in early childhood education, Child Development or a related field","Clearance of background check as required by local, state, and federal regulations","Physical examination and diagnostic tests as required by local, state, and federal regulations","A drug screen and bi-annual TB tests are required as a condition of continual employment","Full Covid-19 vaccination is required as a condition of employment","Must be able to physically interact with children, including bending, kneeling, sitting on the floor, lifting up to 40 pounds, climbing and walking","Must have advanced command of the English language and grammar, both verbal and written","Must remain abreast of developments in the child development field to enhance professional growth and development"],"Responsibilities":["The Infant-Toddler Assistant Teacher is responsible for contributing to the planning, implementation and coordination of the comprehensive education program","The Assistant Teacher supports the Lead Teacher in ensuring that the education program is developmentally appropriate and meets the individual needs of the children as mandated by Early Head Start, state and local standards and the Educare model","Participate in training to build an understanding of the Educare Model","Participate in the local evaluation and national Educare Implementation Study, engaging in a system of reciprocal, regular data feedback and utilization for individualized planning for children and families and continuous program improvement","Participate in Reflective Practice and Supervision throughout the program","Provide a high-quality early learning program that incorporates evidence-based curriculum and instructional activities","Support and provide continuity of care to help infants and toddlers develop secure relationships","Implement, document, and demonstrate an understanding of the importance of multiple perspectives and have the skills to be successful in their interdisciplinary efforts","Collaborate with the Family Engagement Specialist (assigned to each child), and other Educare personnel and support staff to promote individual children's goals relating to early communication development, fine and gross motor skills, development of social and self-care skills","Participate in Family Child Service Reviews as scheduled","In support of ongoing, intensive professional development, Assistant Teachers will attend and participate in all scheduled trainings, engage in coaching cycles with their Lead Teachers, and develop individual plans for their own professional development","Provide an enhanced curriculum focus on: social emotional development, early language and literacy, physical development, and integration of the arts","Engage positively with the children and use appropriate discipline methods as outlined in the school's child guidance discipline policy","Assist in the planning and implementation of learning experiences that promote all developmental domains (social, emotional, physical, and intellectual) including contributing to the readiness of children to enter school by developing their early language acquisition and vocabulary","Assist in developing and managing an attractive and engaging environment that encourages exploration and fosters independence","Position themselves strategically in all environments to actively engage children, provide optimal supervision, and facilitate play","Use the playground as an extension of the classroom; ensure that the playground is safe","Assist in daily routines such as bottle feedings, meal preparations, diapering, toileting, hand washing, monitoring sleep times, cleanup, and supervision of children at all times, including outdoor play","Collaborate with the teaching team to observe, document, and assess their primary care children","Identify any developmental concerns for primary care children and share the information with the Lead Teacher","Collaborate with the teaching team to develop activities and use instructional materials suitable for infants and toddlers with a wide range of cognitive, physical, and emotional maturities","Participate in Family Child Service Reviews for their primary children","Assist in the completion of band-aid reports and documentation of incidents in the medical log","Develop effective partnerships with families by maintaining open communication and encouraging their input into the educational program","Collaborate with the teaching team to develop, document, and implement, in collaboration with each child\u2019s family, an individualized plan for each child to be reviewed regularly in response to each child\u2019s progress","Under the direction of the Lead Teacher, and as feasible, participate in home visits and parent conferences","The Assistant Teacher will assume the responsibilities of the Lead Teacher in the absence of the Lead Teacher","Under the direction of the Lead Teacher, assist in data entry as requested","Assist the Lead Teacher to maintain an up to date classroom inventory","Participate in reflective supervision with the Lead Teacher and\/or Master Teacher","Perform other duties as assigned within the scope of the job description","Responsible for contributing to the planning, implementation and coordination of the comprehensive education program","Supports the Lead Teacher in ensuring that the education program is developmentally appropriate and meets the individual needs of the children as mandated by Head Start, state and local standards, and the Educare model","Assist with the implementation of all program requirements in adherence to performance and outcome standards, along with compliance standards, as prescribed by the multiple funding and model requirements"]},"job_onet_soc":"25904100","job_onet_job_zone":"3"},{"job_id":"nGGoM0NoYFDnLNHWAAAAAA==","job_title":"SY2025-26 Pre-K Teacher","employer_name":"Ingenuity Prep","employer_logo":"https:\/\/encrypted-tbn0.gstatic.com\/images?q=tbn:ANd9GcTD_mpFJDehgFKTr6OLIiIvxkN6dgDbLNPxy1W0&s=0","employer_website":"https:\/\/www.ingenuityprep.org","job_publisher":"LinkedIn","job_employment_type":"Full-time","job_employment_types":["FULLTIME"],"job_apply_link":"https:\/\/www.linkedin.com\/jobs\/view\/sy2025-26-pre-k-teacher-at-ingenuity-prep-4307651440?utm_campaign=google_jobs_apply&utm_source=google_jobs_apply&utm_medium=organic","job_apply_is_direct":false,"apply_options":[{"publisher":"LinkedIn","apply_link":"https:\/\/www.linkedin.com\/jobs\/view\/sy2025-26-pre-k-teacher-at-ingenuity-prep-4307651440?utm_campaign=google_jobs_apply&utm_source=google_jobs_apply&utm_medium=organic","is_direct":false},{"publisher":"SimplyHired","apply_link":"https:\/\/www.simplyhired.com\/job\/1tku9CARF6MrlHyH-6U3RgYcVvBDbAoMV5JQbCrXulELH9zFxWHokQ?utm_campaign=google_jobs_apply&utm_source=google_jobs_apply&utm_medium=organic","is_direct":false},{"publisher":"Teal","apply_link":"https:\/\/www.tealhq.com\/job\/pre-k-teacher_145484e4-90e4-4579-8922-1dd0008629b2?utm_campaign=google_jobs_apply&utm_source=google_jobs_apply&utm_medium=organic","is_direct":false},{"publisher":"BeBee","apply_link":"https:\/\/us.bebee.com\/job\/e52836a5b2f88b94c31582f8e1821d41?utm_campaign=google_jobs_apply&utm_source=google_jobs_apply&utm_medium=organic","is_direct":false},{"publisher":"Jobrapido","apply_link":"https:\/\/us.jobrapido.com\/jobpreview\/1364684302347927552?utm_campaign=google_jobs_apply&utm_source=google_jobs_apply&utm_medium=organic","is_direct":true}],"job_description":"Ingenuity Prep prepares PreK, Elementary, Middle school students in Ward 8 to succeed in college and beyond as impactful civic leaders. Our innovative instructional model promotes small group learning for students, collaborative teaching teams, and robust coaching and professional development opportunities for teachers. Our teacher career ladder rewards strong performance over time, giving teachers the opportunity to earn higher levels of base compensation and bonuses as they demonstrate effectiveness with their students and colleagues. Our instructional leaders are charged with supporting teachers by providing clear expectations, ongoing feedback, and targeted development.\n\nWe are looking for a Pre-K Teacher who is deeply committed to students, has a passion for academic rigor and civic leadership, and wants to work closely with their colleagues to continue to build our program for Ingenuity Prep's students and families during the 2025-2026 school year.\n\nWHAT WE'RE ABOUT\n\u2022 Mission: We're closing the opportunity gap. Students and families in Southeast D.C. have too few options for high-quality elementary, middle, and high schools. Ingenuity Prep aspires to right this systemic injustice providing an exemplary educational option for Southeast D.C.'s students and families.\n\u2022 Model: We pair high expectations with high support. Too often, our students are underestimated. At Ingenuity Prep, an innovative teacher development model, paired with best-in-class training from strong instructional leaders, allows us to grow great teachers who, ultimately, lead high-expectation and high-support classrooms.\n\u2022 Results: Our students are defying expectations. Ingenuity Prep's students outperform their neighborhood peers on rigorous, national, college-track assessments. Already out-performing many of their more privileged peers around the city, in the coming years, Ingenuity Prep's students will provide an expectation-defying and achievement-gap-closing proof point \u2014 showing what our kids are capable of when we provide the right opportunities, expectations, and support.\n\nWHAT YOU'LL DO\n\nAs a Pre-K Teacher at Ingenuity Prep, you will:\n\u2022 Lead effective whole and small group instruction for students by planning and executing engaging and rigorous lessons based on provided curriculum.\n\u2022 Create a joyful, efficient, learning-focused classroom experience for students that leads to exemplary student growth -- both in academic achievement and in leadership skills.\n\u2022 Create a strong classroom culture built on trusting relationships and effective, efficient routines and procedures.\n\u2022 Engage in ongoing data analysis and lesson revision to ensure you are meeting all students academic needs, including daily exit ticket review and weekly assessment analysis.\n\u2022 Collaborate with colleagues to build an effective co-teaching relationship that ensures all students' academic and social emotional needs are met throughout the day.\n\u2022 Communicate and work closely with students' families.\n\u2022 Receive regular, individualized coaching from IP's instructional leadership team to grow your practice.\n\nWHO WE'RE LOOKING FOR\n\nIngenuity Prep may be the right fit for you if:\n\u2022 You have experience and\/or desire to serve as a lead early childhood school teacher in a low-income school.\n\u2022 You have a passion for providing rigorous instruction for students\n\u2022 You want to work closely with your peers in a collaborative teaching setting.\n\u2022 You want to work in a feedback-rich culture, and are eager to grow your practice through individual coaching and professional development opportunities.\n\u2022 You have a history of effectively using academic data to drive whole-group and small-group instruction.\n\u2022 You believe effective instruction is full of joy and rigor.\n\u2022 You have consistently built strong relationships with students and partnered with families as part of your plan for student success.\n\u2022 You have a track record of holding high expectations for yourself and your students.\n\nMORE ABOUT US\n\nIngenuity Prep offers among the strongest compensation and benefits packages of any public charter school in Washington, D.C. Our compensation and benefits package includes:\n\u2022 Highly competitive compensation.\n\u2022 100% of medical and dental premiums for employees paid for by Ingenuity Prep, along with 100% of dependent premiums.\n\u2022 100% of employee's short and long-term disability and life insurance plans paid for by Ingenuity Prep.\n\u2022 A minimum of two weeks maternity\/paternity leave, up to 6 weeks, at 100% of pay (60% from IP and remaining pay from DC Paid Family Leave ) for all staff \u2014 regardless of gender.\n\u2022 A 100% match -- up to 3% -- on your 401K retirement plan.\n\u2022 A 100% Ingenuity Prep-paid cell phone plan. You can even bring your current number into our plan.\n\u2022 MacBook Air computer for professional and personal use.\n\nSalary: $64,890 - $81,039 (commensurate with 1-10 years of experience)\n\nIngenuity Prep does not make hiring decisions on the basis of race, color, creed, ethnicity, national origin, gender, gender identity, sexual orientation, socio-economic background, age, disability, veteran status, religion, political affiliation or any other characteristic protected by state, federal, or local law. However, at this time we do not provide job sponsorship for international candidates, and proof of COVID-19 vaccination is required prior to the first day of employment.","job_is_remote":false,"job_posted_at":"26 days ago","job_posted_at_timestamp":1760572800,"job_posted_at_datetime_utc":"2025-10-16T00:00:00.000Z","job_location":"Washington, DC","job_city":"Washington","job_state":"District of Columbia","job_country":"US","job_latitude":38.9071923,"job_longitude":-77.0368707,"job_benefits":["health_insurance","dental_coverage"],"job_google_link":"https:\/\/www.google.com\/search?q=jobs&gl=us&hl=en&udm=8#vhid=vt%3D20\/docid%3DnGGoM0NoYFDnLNHWAAAAAA%3D%3D&vssid=jobs-detail-viewer","job_min_salary":64890,"job_max_salary":81039,"job_salary_period":"YEAR","job_highlights":{"Qualifications":["You have experience and\/or desire to serve as a lead early childhood school teacher in a low-income school","You have a passion for providing rigorous instruction for students","You want to work closely with your peers in a collaborative teaching setting","You want to work in a feedback-rich culture, and are eager to grow your practice through individual coaching and professional development opportunities","You have a history of effectively using academic data to drive whole-group and small-group instruction","You believe effective instruction is full of joy and rigor","You have consistently built strong relationships with students and partnered with families as part of your plan for student success","You have a track record of holding high expectations for yourself and your students","Ingenuity Prep does not make hiring decisions on the basis of race, color, creed, ethnicity, national origin, gender, gender identity, sexual orientation, socio-economic background, age, disability, veteran status, religion, political affiliation or any other characteristic protected by state, federal, or local law"],"Benefits":["Our teacher career ladder rewards strong performance over time, giving teachers the opportunity to earn higher levels of base compensation and bonuses as they demonstrate effectiveness with their students and colleagues","Model: We pair high expectations with high support","Ingenuity Prep offers among the strongest compensation and benefits packages of any public charter school in Washington, D.C. Our compensation and benefits package includes:","Highly competitive compensation","100% of medical and dental premiums for employees paid for by Ingenuity Prep, along with 100% of dependent premiums","100% of employee's short and long-term disability and life insurance plans paid for by Ingenuity Prep","A minimum of two weeks maternity\/paternity leave, up to 6 weeks, at 100% of pay (60% from IP and remaining pay from DC Paid Family Leave ) for all staff \u2014 regardless of gender","A 100% match -- up to 3% -- on your 401K retirement plan","A 100% Ingenuity Prep-paid cell phone plan","You can even bring your current number into our plan","MacBook Air computer for professional and personal use","Salary: $64,890 - $81,039 (commensurate with 1-10 years of experience)"],"Responsibilities":["Lead effective whole and small group instruction for students by planning and executing engaging and rigorous lessons based on provided curriculum","Create a joyful, efficient, learning-focused classroom experience for students that leads to exemplary student growth -- both in academic achievement and in leadership skills","Create a strong classroom culture built on trusting relationships and effective, efficient routines and procedures","Engage in ongoing data analysis and lesson revision to ensure you are meeting all students academic needs, including daily exit ticket review and weekly assessment analysis","Collaborate with colleagues to build an effective co-teaching relationship that ensures all students' academic and social emotional needs are met throughout the day","Communicate and work closely with students' families","Receive regular, individualized coaching from IP's instructional leadership team to grow your practice"]},"job_onet_soc":"25201100","job_onet_job_zone":"3"},{"job_id":"d-wibDNTZaxAnherAAAAAA==","job_title":"Social Studies Teacher","employer_name":"Elizabeth Seton High School","employer_logo":null,"employer_website":"https:\/\/www.setonhs.org","job_publisher":"Southern Teachers","job_employment_type":"Part-time","job_employment_types":["PARTTIME"],"job_apply_link":"https:\/\/southernteachers.com\/k12teachingjobs\/detail?jobId=75193&jobTitle=Social%2BStudies%2BTeacher&utm_campaign=google_jobs_apply&utm_source=google_jobs_apply&utm_medium=organic","job_apply_is_direct":false,"apply_options":[{"publisher":"Southern Teachers","apply_link":"https:\/\/southernteachers.com\/k12teachingjobs\/detail?jobId=75193&jobTitle=Social%2BStudies%2BTeacher&utm_campaign=google_jobs_apply&utm_source=google_jobs_apply&utm_medium=organic","is_direct":false},{"publisher":"Learn4Good","apply_link":"https:\/\/www.learn4good.com\/jobs\/bladensburg\/maryland\/education\/4431098759\/e\/?utm_campaign=google_jobs_apply&utm_source=google_jobs_apply&utm_medium=organic","is_direct":false}],"job_description":"SOCIAL STUDIES TEACHER\n\nElizabeth Seton High School (ESHS) is a Catholic, secondary, college preparatory school for young women founded in 1959 by the Daughters of Charity. Located in Prince George\u2019s County, a suburb of Washington, DC, the school attracts students from surrounding counties and the District of Columbia. ESHS is committed to providing students with an integrated program that stresses moral values, academic excellence, civic responsibility, and community service. The community reflects a broad ethnic, cultural, and economic diversity contributing to the rich learning environment. For more information about the school, including our guiding principles, please visit www.setonhs.org.\n\nJob Summary\n\nWe are actively seeking a Social Studies teacher for SY25-26. Applicants should be capable and comfortable teaching Social Studies courses across our curriculum (extremely critical). Core subjects include Government, U.S. History, World History and\/or elective courses: Psychology and Sociology. We are searching for a professional educator to serve as a full-time Upper School Social Studies instructor. The Social Studies department is known for its collaboration, creativity, differentiation of instruction and assessment, and commitment to continuous improvement.\n\nThe ideal candidate would have experience and\/or familiarity with Advanced Placement courses and be growth-oriented and open to learning about and teaching in a variety of modalities.\n\nSupervisory Responsibilities\n\u2022 Supervise students in the classroom, on school grounds and educational trips\n\nResponsibilities\n\u2022 Create a classroom culture of high achievement and student ownership of learning that helps foster students\u2019 intellectual, social, and emotional development\n\u2022 Provide daily instruction, including clear learning outcomes, well-designed lessons, and high-quality assessments aligned with ESHS\u2019 curriculum and standards\n\u2022 Practical technology skills, including using ESHS\u2019 learning management systems (Blackbaud and Google Classroom)\n\u2022 Serve as an advisor in the Student Advisory Program\n\u2022 Demonstrate best practices in data-driven instruction, including inquiry and hands-on activities, demonstrations, lectures, and discussions\n\u2022 Communicate regularly with families to identify students\u2019 talents, interests, and needs and update parents regarding students\u2019 achievements and progress\n\u2022 Active commitment to enhancing our school community through involvement in committees and student life activities\n\u2022 Collaborate with school-based staff and the ESHS community in meetings, regular analysis sessions, and professional learning designed to enhance student's learning experience and increase student achievement\n\nRequired Skills and Abilities:\n\u2022 A desire to teach in a Catholic School committed to Catholic education and the formation of young women in Christian character\n\u2022 Ability to teach all levels of study, from College Preparatory to Advanced Placement\n\u2022 Exemplary character and demonstrated services to others\n\u2022 Evidence of strong communication and interpersonal skills\n\u2022 Demonstrate best practices in data-driven instruction, including inquiry and hands-on activities, demonstrations, lectures, and discussions\n\u2022 Creativity and an ability to collaborate with colleagues\n\u2022 Willingness and ability to contribute to an atmosphere and environment conducive to our girls' academic, spiritual, social, and emotional development\n\u2022 Excellent organizational skills and attention to detail\n\nEducation and Experience:\n\u2022 Bachelor\u2019s degree in Education, History, Geography, or a related discipline\n\u2022 Masters in related field preferred\n\u2022 MSDE or certification from another State preferred\n\u2022 Active Social Studies teaching certificate (grades 7-12) desired\n\u2022 One year teaching experience required\n\u2022 Specialized training in teaching secondary school-aged children is preferred\n\nPhysical Requirements:\n\u2022 Must be able to navigate school facilities and lead students to safety in case of an emergency\n\u2022 Must be able to lift to 25 pounds at times\n\nSalary Range:\n\u2022 Based on experience and credentials\n\nElizabeth Seton High School, an Equal Opportunity Employer, does not discriminate based on race, color, national or ethnic origin, age, gender, disability, marital status, sexual orientation, or any other status protected by federal, state, or local law in the administration of its employment practices.","job_is_remote":false,"job_posted_at":null,"job_posted_at_timestamp":null,"job_posted_at_datetime_utc":null,"job_location":"Bladensburg, MD","job_city":"Bladensburg","job_state":"Maryland","job_country":"US","job_latitude":38.9392779,"job_longitude":-76.9338631,"job_benefits":null,"job_google_link":"https:\/\/www.google.com\/search?q=jobs&gl=us&hl=en&udm=8#vhid=vt%3D20\/docid%3Dd-wibDNTZaxAnherAAAAAA%3D%3D&vssid=jobs-detail-viewer","job_salary":null,"job_min_salary":null,"job_max_salary":null,"job_salary_period":null,"job_highlights":{"Qualifications":["Applicants should be capable and comfortable teaching Social Studies courses across our curriculum (extremely critical)","Core subjects include Government, U.S. History, World History and\/or elective courses: Psychology and Sociology","The ideal candidate would have experience and\/or familiarity with Advanced Placement courses and be growth-oriented and open to learning about and teaching in a variety of modalities","A desire to teach in a Catholic School committed to Catholic education and the formation of young women in Christian character","Ability to teach all levels of study, from College Preparatory to Advanced Placement","Exemplary character and demonstrated services to others","Evidence of strong communication and interpersonal skills","Demonstrate best practices in data-driven instruction, including inquiry and hands-on activities, demonstrations, lectures, and discussions","Creativity and an ability to collaborate with colleagues","Willingness and ability to contribute to an atmosphere and environment conducive to our girls' academic, spiritual, social, and emotional development","Excellent organizational skills and attention to detail","Bachelor\u2019s degree in Education, History, Geography, or a related discipline","One year teaching experience required","Must be able to navigate school facilities and lead students to safety in case of an emergency","Must be able to lift to 25 pounds at times"],"Responsibilities":["Supervise students in the classroom, on school grounds and educational trips","Create a classroom culture of high achievement and student ownership of learning that helps foster students\u2019 intellectual, social, and emotional development","Provide daily instruction, including clear learning outcomes, well-designed lessons, and high-quality assessments aligned with ESHS\u2019 curriculum and standards","Practical technology skills, including using ESHS\u2019 learning management systems (Blackbaud and Google Classroom)","Serve as an advisor in the Student Advisory Program","Demonstrate best practices in data-driven instruction, including inquiry and hands-on activities, demonstrations, lectures, and discussions","Communicate regularly with families to identify students\u2019 talents, interests, and needs and update parents regarding students\u2019 achievements and progress","Active commitment to enhancing our school community through involvement in committees and student life activities","Collaborate with school-based staff and the ESHS community in meetings, regular analysis sessions, and professional learning designed to enhance student's learning experience and increase student achievement"]},"job_onet_soc":"25202200","job_onet_job_zone":"4"},{"job_id":"_66wtEnkZpIIbvitAAAAAA==","job_title":"Founding Teacher Leader","employer_name":"DC Wildflower Public Charter School","employer_logo":null,"employer_website":"https:\/\/www.wildflowerschools.org","job_publisher":"Indeed","job_employment_type":"Full-time","job_employment_types":["FULLTIME"],"job_apply_link":"https:\/\/www.indeed.com\/viewjob?jk=fc565beba83f1ea3&utm_campaign=google_jobs_apply&utm_source=google_jobs_apply&utm_medium=organic","job_apply_is_direct":false,"apply_options":[{"publisher":"Indeed","apply_link":"https:\/\/www.indeed.com\/viewjob?jk=fc565beba83f1ea3&utm_campaign=google_jobs_apply&utm_source=google_jobs_apply&utm_medium=organic","is_direct":false},{"publisher":"Glassdoor","apply_link":"https:\/\/www.glassdoor.com\/job-listing\/founding-teacher-leader-dc-wildflower-public-charter-school-JV_IC1138213_KO0,23_KE24,59.htm?jl=1009386910222&utm_campaign=google_jobs_apply&utm_source=google_jobs_apply&utm_medium=organic","is_direct":false},{"publisher":"Glassdoor","apply_link":"https:\/\/www.glassdoor.com.mx\/job-listing\/founding-teacher-leader-dc-wildflower-public-charter-school-JV_IC1138213_KO0,23_KE24,59.htm?jl=1009386910222&utm_campaign=google_jobs_apply&utm_source=google_jobs_apply&utm_medium=organic","is_direct":false},{"publisher":"Ladders","apply_link":"https:\/\/www.theladders.com\/job\/founding-teacher-leader-gusto-washington-dc_84087872?utm_campaign=google_jobs_apply&utm_source=google_jobs_apply&utm_medium=organic","is_direct":false},{"publisher":"SimplyHired","apply_link":"https:\/\/www.simplyhired.com\/job\/OyJGE9GWcZxOcj_7IVyaacQ-L-5hMsNZbdP7rBjT1w7qPPjvRHZp1g?utm_campaign=google_jobs_apply&utm_source=google_jobs_apply&utm_medium=organic","is_direct":false}],"job_description":"Become a founding Teacher Leader of your own Montessori micro-school!\n\nAbout DC Wildflower Public Charter School\n\nDC Wildflower PCS is committed to creating public, intentionally small, authentic Montessori environments that model the world free from oppression. We believe intentionally small, community embedded, teacher-led Montessori learning environments will accelerate the journey for students of the global majority to be and feel safe, seen and heard. DCWPCS is where students\u2019 identities are affirmed and their genius unleashed!\n\nDescription\n\nAre you a dedicated educator who dreams of having more autonomy and creative freedom to foster a vibrant, child-centered learning environment within your classroom? DC Wildflower PCS (DCWPCS) invites you to reimagine the possibilities through its teacher-led tuition free microschool model. We\u2019re seeking passionate and entrepreneurial educators to join us in founding your own microschool site where you\u2019ll lead at the front of the classroom and behind the scenes too. Whether you're already Montessori-trained or aspiring to be, this is a great opportunity to make a lasting impact on your local community and create a classroom where you, your students, and their families truly thrive. Currently there are two microschools operating within DC Wildflower PCS: The Riverseed School (in Ward 7) & blue montessori (in Ward 8). We expect educators will create additional microschools in Wards 4, 5, 7 & 8 over the next three years.\n\nThe Opportunity:\n\nAs a Teacher Leader, you\u2019ll have the opportunity to bring your school vision to life and receive access to support and resources throughout your School Startup Journey - from school planning, opening, and beyond. You\u2019ll have the flexibility to provide instruction and lead day-to-day school operations, offering a unique blend of teaching and leadership. This role provides the autonomy to shape the educational experiences offered within your school and local community, ensuring a nurturing, responsive, and effective learning environment. You\u2019ll also have the support of a robust network dedicated to your professional growth and leadership development. The School Startup Journey typically spans 12-18 months, involving phases where you define your school\u2019s vision, secure a facility, and obtain funding in partnership with the DC charter team.\n\nAbout DC Wildflower PCS:\n\nThe mission of DC Wildflower Public Charter School is to serve a larger, universal purpose in eliminating racial and social discrimination and hierarchy \u2013 and offer an intimate liberatory educational experience. We believe intentionally small, community embedded, teacher-led Montessori learning environments will accelerate the journey for students of the global majority to be and feel safe, seen and heard. DCWPCS is where students\u2019 identities are affirmed and their genius unleashed! Each Wildflower school is small in scale, serving 1-2 classrooms of mixed-age students, and focuses on personalized learning and community involvement. DCWPCS is a member of the Wildflower Schools Network, a national network of over 60 decentralized, teacher-led microschools that provides an intimate and community-driven alternative to traditional education models. All members operate authentic Montessori schools, serving toddler to adolescent students, emphasizing teacher autonomy, hands-on learning, and respect for each child's unique developmental pace. Wildflower Schools seeks to create environments where all children can flourish academically, socially, and emotionally.\n\nWhat We Offer:\n\u2022 Flexibility: Serve as a teacher and leader of your school, and tailor the learning experience to meet your community\u2019s needs.\n\u2022 Impact: Directly influence the educational and personal growth of your students. Bring Montessori pedagogy, for free, to communities that historically have not had access.\n\u2022 Innovation: Be at the forefront of redefining public pedagogy by embracing Montessori\u2019s principles of child independence within scaffolded limits, and small-scale growth of a charter network.\n\u2022 Support: Access to a community of mentors, ongoing professional development, and administrative resources.\n\u2022 Access to Montessori credential training: Grants, like the Black Wildflowers Fund, are available in select states for aspiring Montessori teachers to support your pursuit of Montessori certification.\n\nWho Should Express Interest:\n\nSeasoned and licensed educators who are\n\u2022 already Montessori-trained OR interested in undergoing Montessori training\n\u2022 aligned with Wildflower Schools values, community norms, and principles, and\n\u2022 looking for a blended teaching and leadership role within Washington, DC (Wards 4, 5, 7 & 8)\n\nExpress Interest: To express interest or have someone reach out to answer your questions, submit your resume on our Gusto platform.\n\nSalary\n\n$95,000 - $120,000 per year","job_is_remote":false,"job_posted_at":null,"job_posted_at_timestamp":null,"job_posted_at_datetime_utc":null,"job_location":"Washington, DC","job_city":"Washington","job_state":"District of Columbia","job_country":"US","job_latitude":38.9071923,"job_longitude":-77.0368707,"job_benefits":null,"job_google_link":"https:\/\/www.google.com\/search?q=jobs&gl=us&hl=en&udm=8#vhid=vt%3D20\/docid%3D_66wtEnkZpIIbvitAAAAAA%3D%3D&vssid=jobs-detail-viewer","job_min_salary":95000,"job_max_salary":120000,"job_salary_period":"YEAR","job_highlights":{"Qualifications":["already Montessori-trained OR interested in undergoing Montessori training","aligned with Wildflower Schools values, community norms, and principles, and"],"Benefits":["As a Teacher Leader, you\u2019ll have the opportunity to bring your school vision to life and receive access to support and resources throughout your School Startup Journey - from school planning, opening, and beyond","You\u2019ll also have the support of a robust network dedicated to your professional growth and leadership development","The School Startup Journey typically spans 12-18 months, involving phases where you define your school\u2019s vision, secure a facility, and obtain funding in partnership with the DC charter team","Flexibility: Serve as a teacher and leader of your school, and tailor the learning experience to meet your community\u2019s needs","Impact: Directly influence the educational and personal growth of your students","Bring Montessori pedagogy, for free, to communities that historically have not had access","Support: Access to a community of mentors, ongoing professional development, and administrative resources","Access to Montessori credential training: Grants, like the Black Wildflowers Fund, are available in select states for aspiring Montessori teachers to support your pursuit of Montessori certification","$95,000 - $120,000 per year"],"Responsibilities":["You\u2019ll have the flexibility to provide instruction and lead day-to-day school operations, offering a unique blend of teaching and leadership","This role provides the autonomy to shape the educational experiences offered within your school and local community, ensuring a nurturing, responsive, and effective learning environment"]},"job_onet_soc":"39701100","job_onet_job_zone":"3"},{"job_id":"gYGu8S0QAH0LXA3XAAAAAA==","job_title":"Elementary Lead Teacher (2nd through 4th Grade)","employer_name":"Creative Minds International Public Charter School","employer_logo":"https:\/\/encrypted-tbn0.gstatic.com\/images?q=tbn:ANd9GcSmVBbsJAVtj83TTEbD7mOOVO48Ev0T77wkAfLL&s=0","employer_website":"https:\/\/www.creativemindspcs.org","job_publisher":"ZipRecruiter","job_employment_type":"Full-time","job_employment_types":["FULLTIME"],"job_apply_link":"https:\/\/www.ziprecruiter.com\/c\/Creative-Minds-International-Public-Charter-School\/Job\/Elementary-Lead-Teacher-(2nd-through-4th-Grade)\/-in-Washington,DC?jid=1c702c2b59c41a26&utm_campaign=google_jobs_apply&utm_source=google_jobs_apply&utm_medium=organic","job_apply_is_direct":false,"apply_options":[{"publisher":"ZipRecruiter","apply_link":"https:\/\/www.ziprecruiter.com\/c\/Creative-Minds-International-Public-Charter-School\/Job\/Elementary-Lead-Teacher-(2nd-through-4th-Grade)\/-in-Washington,DC?jid=1c702c2b59c41a26&utm_campaign=google_jobs_apply&utm_source=google_jobs_apply&utm_medium=organic","is_direct":false}],"job_description":"Now accepting applications for School Year 2024-2025\n\nCreative Minds International Public Charter School (CMIPCS) is a tuition-free public charter school located in NW Washington, DC, authorized to serve students from preschool through 8th grade. Now in its ninth year of operation, CMIPCS serves over 500 students in Preschool (3-year-olds) through 8th grade.\n\nOur mission is to provide students with the foundational skills required for successful participation in a global society. CMI is a unique and dynamic working environment with a respectful and positive school culture. We offer a highly-engaging, international curriculum with project- and arts-based activities with an emphasis in STEAM that foster creativity, self-motivation, social and emotional development, and academic excellence.\n\nThe Position:\n\nElementary lead teachers at CMIPCS provide rich, age-appropriate learning experiences for classroom of 2nd - 4th grade students. Elementary Lead teachers, along with 1 assistant teacher, utilize an international curriculum, along with arts-integration and inclusion practices to teach a diverse student body. They encourage and respect individuality, focusing on the development of each child's regulation and engagement in social-emotional learning and academic content. Responsibilities include, but are not limited to:\n\u2022 Establishing clear objectives for all lessons, units, projects, and assessments;\n\u2022 Developing lesson plans that draw content from CMI professional development in the areas of arts integration and child development to reinforce student learning;\n\u2022 Using a variety of instructional materials, resources, and experiences to enrich student learning;\n\u2022 Meeting the needs, interests and abilities for all students, including students with disabilities, ELL students, and those who are gifted and talented;\n\u2022 Administering CMI's developmental assessment for each child and tracking students' progress through the developmental milestones required for successful communication, self-regulation, and social interaction;\n\u2022 Regularly observing students and taking anecdotal notes to inform planning in the arrangement of small groups, classroom set up, integrations of students' interests in learning activities, and subsequent assessments;\n\u2022 Monitoring student progress through frequent formal and informal student evaluations recorded in portfolio assessments;\n\u2022 Providing educational opportunities that reflects an understanding of students' unique sensory and information processing profiles;\n\u2022 Using appropriate techniques and strategies that promote and enhance creative problem-solving, and evaluative thinking of students;\n\u2022 Working with families to support the progress of individual students;\n\u2022 Valuing the importance of play and providing opportunities for child-initiated explorations in the classroom throughout the day;\n\u2022 Using effective, positive, respectful interpersonal communication skills;\n\u2022 Establishing positive relationships with colleagues, students, families and the community which reflect recognition of and respect for every individual;\n\u2022 Willingness or experience incorporating instructional technology into practice;\n\u2022 Attend a two-week summer institute and other required professional development sessions.\n\nDesired Qualities\n\u2022 Excellent verbal\/written communication skills;\n\u2022 Demonstrated ability to engage the interest of school-age children;\n\u2022 Prior teaching experience, preferably in an elementary urban setting;\n\u2022 Demonstrated ability to work well with parents;\n\u2022 Demonstrated ability to work effectively with teaching teams;\n\u2022 Patience, flexibility, and a willingness to take risks;\n\u2022 Consistently reflects on her\/his own teaching practices;\n\u2022 Experience working with linguistically and ethnically diverse student populations and children with developmental differences;\n\u2022 Demonstrated commitment to professional growth and eagerness to learn;\n\u2022 Demonstrated commitment to the well-being and success of all students.\n\nMinimum Qualifications:\n\u2022 Bachelor's degree (required), Education degree (preferred);\n\u2022 Praxis I; Elementary Praxis II (successful completion preferred, eligibility required);\n\nCreative Minds International PCS is an Equal Opportunity Employer. Personnel are chosen on the basis of ability without regard to race, color, religion, sex, national origin, disability, marital status or sexual orientation, in accordance with federal and state law.","job_is_remote":false,"job_posted_at":null,"job_posted_at_timestamp":null,"job_posted_at_datetime_utc":null,"job_location":"Washington, DC","job_city":"Washington","job_state":"District of Columbia","job_country":"US","job_latitude":38.9071923,"job_longitude":-77.0368707,"job_benefits":null,"job_google_link":"https:\/\/www.google.com\/search?q=jobs&gl=us&hl=en&udm=8#vhid=vt%3D20\/docid%3DgYGu8S0QAH0LXA3XAAAAAA%3D%3D&vssid=jobs-detail-viewer","job_salary":null,"job_min_salary":null,"job_max_salary":null,"job_salary_period":null,"job_highlights":{"Qualifications":["Establishing positive relationships with colleagues, students, families and the community which reflect recognition of and respect for every individual;","Willingness or experience incorporating instructional technology into practice;","Attend a two-week summer institute and other required professional development sessions"],"Responsibilities":["Elementary lead teachers at CMIPCS provide rich, age-appropriate learning experiences for classroom of 2nd - 4th grade students","Elementary Lead teachers, along with 1 assistant teacher, utilize an international curriculum, along with arts-integration and inclusion practices to teach a diverse student body","They encourage and respect individuality, focusing on the development of each child's regulation and engagement in social-emotional learning and academic content","Establishing clear objectives for all lessons, units, projects, and assessments;","Developing lesson plans that draw content from CMI professional development in the areas of arts integration and child development to reinforce student learning;","Using a variety of instructional materials, resources, and experiences to enrich student learning;","Meeting the needs, interests and abilities for all students, including students with disabilities, ELL students, and those who are gifted and talented;","Administering CMI's developmental assessment for each child and tracking students' progress through the developmental milestones required for successful communication, self-regulation, and social interaction;","Regularly observing students and taking anecdotal notes to inform planning in the arrangement of small groups, classroom set up, integrations of students' interests in learning activities, and subsequent assessments;","Monitoring student progress through frequent formal and informal student evaluations recorded in portfolio assessments;","Providing educational opportunities that reflects an understanding of students' unique sensory and information processing profiles;","Using appropriate techniques and strategies that promote and enhance creative problem-solving, and evaluative thinking of students;","Working with families to support the progress of individual students;","Valuing the importance of play and providing opportunities for child-initiated explorations in the classroom throughout the day;","Using effective, positive, respectful interpersonal communication skills;"]},"job_onet_soc":"25202100","job_onet_job_zone":"4"},{"job_id":"-EV-gA-Iw8ftftT2AAAAAA==","job_title":"Assistant Teacher - Infants","employer_name":"Bright Beginnings Inc","employer_logo":null,"employer_website":null,"job_publisher":"Indeed","job_employment_type":"Full-time","job_employment_types":["FULLTIME"],"job_apply_link":"https:\/\/www.indeed.com\/viewjob?jk=8cc457dd503d47fd&utm_campaign=google_jobs_apply&utm_source=google_jobs_apply&utm_medium=organic","job_apply_is_direct":true,"apply_options":[{"publisher":"Indeed","apply_link":"https:\/\/www.indeed.com\/viewjob?jk=8cc457dd503d47fd&utm_campaign=google_jobs_apply&utm_source=google_jobs_apply&utm_medium=organic","is_direct":true}],"job_description":"Bright Beginnings, Inc. is a non-profit organization that operates early childhood and family learning centers for families in Washington, DC. Using a two-generation approach, Bright Beginnings Inc. works to ensure every child experiencing housing instability is healthy, safe, engaged, supported, and challenged; develop school-ready and kindergarten-prepared children; support families in breaking the cycle of inter-generational poverty; and partner intentionally to eradicate disparities and remove obstacles to economic mobility.\n\nSummary: Responsible for developing and implementing an ongoing program of activities that promote the social, emotional, cognitive, and physical development of each child enrolled in preschool. programming, in accordance with Head Start Performance Standards and Title 29 of the District of Columbia Municipal Regulations (DCMR).\n\nEssential Duties:\n\n1. Support team meetings with lead teacher, child development assistant, and parent aide to develop weekly lesson plans and activities that address the individual goals of children.\n\n2. Support the day-to-day supervision and support of child development assistants, substitutes, parent aides, and volunteers, which includes sharing daily lesson plans and discussing goals for children.\n\n3. Meet regularly with the Lead Teacher, Master Teacher\/Instructional Coach, and Education Director to review curriculum plans and activities, improve classroom instructional practice, and assess program effectiveness.\n\n4. Support the implementation of Head Start Performance Standards, National Association of the Education of Young Children\u2019s (NAEYC) Accreditation Standards, and Title 29: DCMR performance standards, policies and procedures, regulations and guidelines in the day-to-day operation of a prekindergarten program (ages 3-5), including the implementation of developmentally appropriate practices.\n\n5. Support the implementation of the evidenced-based curriculum, High Scope, with fidelity and according to BBI policies and procedures.\n\n6. Collaborate with classroom staff to plan and implement the daily program of activities based on principles of child development and under the High Scope curriculum.\n\n7. Support the implementation of the Bright Beginnings\u2019 Closing the Word Gap Initiative with regular use of LENA devices.\n\n8. Work with classroom staff to create daily open-ended small groups for children to encourage questioning, problem-solving, language, creativity, and concept forming in young children.\n\n9. Support the implementation of developmental, behavioral, and sensory screenings as mandated by Head Start, OSSE, and NAEYC regulations and performance standards.\n\n10. Collect relevant data to support a referral to the Multidisciplinary Team Coordinator for children suspected of delays or disabilities.\n\n11. Assure parents or designees sign in and out daily by greeting each child and parent individually at the time of arrival and departure.\n\n12. Support the maintenance of the portfolio and record of each child\u2019s progress and development to demonstrate student learning, plan individual instruction, and comply with Head Start Standards.\n\n13. Collaborate with a multi-disciplinary team to fully implement an Individual Family Service Plan (IFSP) or Individual Education Plan (IEP) for children with disabilities.\n\n14. Attend all staff meetings and professional learning provided by Bright Beginnings.\n\n15. Observe each child daily to assess skills, interests, and needs and use this information to facilitate learning and growth. Document daily observations in the child\u2019s portfolio, which is used to inform the quarterly assessments.\n\nJob Description \u2013 PreK Assistant Teacher (Head Start) 2\n\n16. Support the administration of the Child Observation Record (COR) three times per year (Fall, Winter, and Spring); enter observations into the COR database system and utilize the results of the COR to personalize and individualize weekly lesson plans.\n\n17. Establish a positive relationship with each child\u2019s family and share information about the child\u2019s day at school with the child\u2019s parent(s).\n\n18. Inform and facilitate parent understanding of the child\u2019s progress toward meeting developmental objectives determined by the COR and develop individual lesson plans to promote each child\u2019s growth and development.\n\n19. Provide home-to-school activities to reinforce the center\u2019s lesson plans in the home setting.\n\n20. Ensure universal precautions are kept at all times, including washing of hands upon entering the classroom, after diapering, toileting, before and after meals, and after contact with bodily fluids.\n\n21. Support the maintenance of classroom and facility, in a safe and sanitary condition by completing daily health and safety checklists of classrooms and playground.\n\n22. Implement health procedures daily, including following medication administration procedures, tooth brushing, sanitation, and administering First Aid\/CPR.\n\n23. Assist with evacuation of children during fire drills, natural disasters, and any other emergencies, which may occur.\n\n24. Set up and maintain a well-organized, safe, and attractive classroom environment conducive to the optimal growth and development of children.\n\n25. Develop a positive relationship with each child and promote the development of self-esteem and self-discipline.\n\n26. Interact and closely supervise children outdoors.\n\n27. Conduct parent-teacher conferences and home visits with parents and children in the assigned classroom to discuss each child\u2019s growth and development.\n\n28. Attend all staff meetings and professional learning provided by Bright Beginnings.\n\n29. Keep abreast of current knowledge in the field of Early Childhood Education.\n\n30. Maintains confidentiality of children and families at all times.\n\n31. Other duties as assigned.\n\nQualifications:\n\u2022 Mission and culture alignment;\n\u2022 Associate\u2019s degree in Early Childhood Education or associate\u2019s degree in a related field with 15 credits in Early Childhood Education. At least one year of teaching experience;\n\u2022 Ability to relate positively to young children, parents, and staff;\n\u2022 Strong working knowledge of Head Start Program Performance Standards and NAEYC guidelines and regulations;\n\u2022 Prefer knowledge of High Scope curriculum or other evidenced-based early childhood education curricula;\n\u2022 Demonstrate success in working as a member of a team;\n\u2022 Effective and strong communication skills (orally and written);\n\u2022 Strong computer skills with expertise in Windows-based programs, such as the Microsoft Office Suite;\n\u2022 Must have DC local and Federal criminal record clearance, Child Protective Register check status, and substance abuse testing; and\n\u2022 Documentation of Tuberculin-free condition and health screening on an annual basis.\n\nPhysical Demands:\n\u2022 Be able to lift 25-50 lbs.\n\u2022 Be able to walk, squat\/kneel, sit on the floor, see, hear, and speak.\n\u2022 Be able to raise objects from a lower to a higher location or move objects horizontally from one location to another.\n\u2022 Be able to sit for extended periods in front of a computer.","job_is_remote":false,"job_posted_at":null,"job_posted_at_timestamp":null,"job_posted_at_datetime_utc":null,"job_location":"Washington, DC","job_city":"Washington","job_state":"District of Columbia","job_country":"US","job_latitude":38.9071923,"job_longitude":-77.0368707,"job_benefits":null,"job_google_link":"https:\/\/www.google.com\/search?q=jobs&gl=us&hl=en&udm=8#vhid=vt%3D20\/docid%3D-EV-gA-Iw8ftftT2AAAAAA%3D%3D&vssid=jobs-detail-viewer","job_min_salary":54262,"job_max_salary":63838,"job_salary_period":"YEAR","job_highlights":{"Qualifications":["Mission and culture alignment;","Associate\u2019s degree in Early Childhood Education or associate\u2019s degree in a related field with 15 credits in Early Childhood Education","At least one year of teaching experience;","Ability to relate positively to young children, parents, and staff;","Strong working knowledge of Head Start Program Performance Standards and NAEYC guidelines and regulations;","Prefer knowledge of High Scope curriculum or other evidenced-based early childhood education curricula;","Demonstrate success in working as a member of a team;","Effective and strong communication skills (orally and written);","Strong computer skills with expertise in Windows-based programs, such as the Microsoft Office Suite;","Must have DC local and Federal criminal record clearance, Child Protective Register check status, and substance abuse testing; and","Documentation of Tuberculin-free condition and health screening on an annual basis","Be able to lift 25-50 lbs","Be able to walk, squat\/kneel, sit on the floor, see, hear, and speak","Be able to raise objects from a lower to a higher location or move objects horizontally from one location to another","Be able to sit for extended periods in front of a computer"],"Responsibilities":["Summary: Responsible for developing and implementing an ongoing program of activities that promote the social, emotional, cognitive, and physical development of each child enrolled in preschool. programming, in accordance with Head Start Performance Standards and Title 29 of the District of Columbia Municipal Regulations (DCMR)","Support team meetings with lead teacher, child development assistant, and parent aide to develop weekly lesson plans and activities that address the individual goals of children","Support the day-to-day supervision and support of child development assistants, substitutes, parent aides, and volunteers, which includes sharing daily lesson plans and discussing goals for children","Meet regularly with the Lead Teacher, Master Teacher\/Instructional Coach, and Education Director to review curriculum plans and activities, improve classroom instructional practice, and assess program effectiveness","Support the implementation of Head Start Performance Standards, National Association of the Education of Young Children\u2019s (NAEYC) Accreditation Standards, and Title 29: DCMR performance standards, policies and procedures, regulations and guidelines in the day-to-day operation of a prekindergarten program (ages 3-5), including the implementation of developmentally appropriate practices","Support the implementation of the evidenced-based curriculum, High Scope, with fidelity and according to BBI policies and procedures","Collaborate with classroom staff to plan and implement the daily program of activities based on principles of child development and under the High Scope curriculum","Support the implementation of the Bright Beginnings\u2019 Closing the Word Gap Initiative with regular use of LENA devices","Work with classroom staff to create daily open-ended small groups for children to encourage questioning, problem-solving, language, creativity, and concept forming in young children","Support the implementation of developmental, behavioral, and sensory screenings as mandated by Head Start, OSSE, and NAEYC regulations and performance standards","Collect relevant data to support a referral to the Multidisciplinary Team Coordinator for children suspected of delays or disabilities","Assure parents or designees sign in and out daily by greeting each child and parent individually at the time of arrival and departure","Support the maintenance of the portfolio and record of each child\u2019s progress and development to demonstrate student learning, plan individual instruction, and comply with Head Start Standards","Collaborate with a multi-disciplinary team to fully implement an Individual Family Service Plan (IFSP) or Individual Education Plan (IEP) for children with disabilities","Attend all staff meetings and professional learning provided by Bright Beginnings","Observe each child daily to assess skills, interests, and needs and use this information to facilitate learning and growth","Document daily observations in the child\u2019s portfolio, which is used to inform the quarterly assessments","Job Description \u2013 PreK Assistant Teacher (Head Start) 2","Support the administration of the Child Observation Record (COR) three times per year (Fall, Winter, and Spring); enter observations into the COR database system and utilize the results of the COR to personalize and individualize weekly lesson plans","Establish a positive relationship with each child\u2019s family and share information about the child\u2019s day at school with the child\u2019s parent(s)","Inform and facilitate parent understanding of the child\u2019s progress toward meeting developmental objectives determined by the COR and develop individual lesson plans to promote each child\u2019s growth and development","Provide home-to-school activities to reinforce the center\u2019s lesson plans in the home setting","Ensure universal precautions are kept at all times, including washing of hands upon entering the classroom, after diapering, toileting, before and after meals, and after contact with bodily fluids","21. Support the maintenance of classroom and facility, in a safe and sanitary condition by completing daily health and safety checklists of classrooms and playground","Implement health procedures daily, including following medication administration procedures, tooth brushing, sanitation, and administering First Aid\/CPR","Assist with evacuation of children during fire drills, natural disasters, and any other emergencies, which may occur","Set up and maintain a well-organized, safe, and attractive classroom environment conducive to the optimal growth and development of children","Develop a positive relationship with each child and promote the development of self-esteem and self-discipline","26. Interact and closely supervise children outdoors","Conduct parent-teacher conferences and home visits with parents and children in the assigned classroom to discuss each child\u2019s growth and development","Attend all staff meetings and professional learning provided by Bright Beginnings","Keep abreast of current knowledge in the field of Early Childhood Education","30. Maintains confidentiality of children and families at all times","Other duties as assigned"]},"job_onet_soc":"25201100","job_onet_job_zone":"3"}]}